[
    {
        "매물번호": "2513937863",
        "매물유형": "오피스텔",
        "거래유형": "전세",
        "가격": "2억 3,000",
        "소재지": "서울시 동작구 노량진동 16-1",
        "매물특징": "모든대출가능.보증보헙됨,HF,전입신고 됨,전세권설정됨,버팀목안됨",
        "공급/전용면적": "",
        "해당층/총층": "13/18층",
        "방수/욕실수": "1/1개",
        "관리비": "10만원 상세보기",
        "입주 가능일": "2025년 6월 1일 협의가능",
        "방향": "동향(거실 기준)",
        "URL": "https://new.land.naver.com/houses?articleNo=2513937863",
        "메인사진": null
    },
    {
        "매물번호": "2513536770",
        "매물유형": "오피스텔",
        "거래유형": "전세",
        "가격": "2억 2,000",
        "소재지": "서울시 동작구 노량진동 16-1",
        "매물특징": "남쪽 항상햇빛",
        "공급/전용면적": "",
        "해당층/총층": "6/18층",
        "방수/욕실수": "1/1개",
        "관리비": "12만원 상세보기",
        "입주 가능일": "2025년 05월 중순 협의가능",
        "방향": "남향(거실 기준)",
        "URL": "https://new.land.naver.com/houses?articleNo=2513536770",
        "메인사진": null
    },
    {
        "매물번호": "2514149721",
        "매물유형": "오피스텔",
        "거래유형": "월세",
        "가격": "1,000/79",
        "소재지": "서울시 동작구 노량진동 16-1",
        "매물특징": "전입가능합니다 3월22월입주가능합니다.",
        "공급/전용면적": "",
        "해당층/총층": "6/18층",
        "방수/욕실수": "1/1개",
        "관리비": "13만원 상세보기",
        "입주 가능일": "2025년 3월 22일",
        "방향": "동향(거실 기준)",
        "URL": "https://new.land.naver.com/houses?articleNo=2514149721",
        "메인사진": "https://landthumb-phinf.pstatic.net/20250318_254/1742267617711fu9lP_JPEG/20210217_080610.jpg?type=m400_350"
    },
    {
        "매물번호": "2512716609",
        "매물유형": "오피스텔",
        "거래유형": "월세",
        "가격": "1,000/85",
        "소재지": "서울시 동작구 노량진동 16-1",
        "매물특징": "신축급풀옵션오피스텔,전입신고가능,자주식주차,생활편리,지하철바로앞",
        "공급/전용면적": "",
        "해당층/총층": "5/18층",
        "방수/욕실수": "1/1개",
        "관리비": "12만원 상세보기",
        "입주 가능일": "2025년 4월 27일",
        "방향": "북향(안방 기준)",
        "URL": "https://new.land.naver.com/houses?articleNo=2512716609",
        "메인사진": "https://landthumb-phinf.pstatic.net/20250311_286/1741655749488pCcV0_JPEG/20200724_075348.jpg?type=m400_350"
    },
    {
        "매물번호": "2514432822",
        "매물유형": "오피스텔",
        "거래유형": "월세",
        "가격": "1,000/82",
        "소재지": "서울시 동작구 노량진동 16-1",
        "매물특징": "북향, 한강뷰, 전입신고가능, 최저가 매물",
        "공급/전용면적": "",
        "해당층/총층": "13/18층",
        "방수/욕실수": "1/1개",
        "관리비": "13만원 상세보기",
        "입주 가능일": "2025년 04월 중순 협의가능",
        "방향": "북향(안방 기준)",
        "URL": "https://new.land.naver.com/houses?articleNo=2514432822",
        "메인사진": "https://landthumb-phinf.pstatic.net/20250318_203/1742280508406Je4VN_JPEG/KakaoTalk_20210316_161704029_02.jpg?type=m400_350"
    },
    {
        "매물번호": "2513864154",
        "매물유형": "오피스텔",
        "거래유형": "월세",
        "가격": "1,000/80",
        "소재지": "서울시 동작구 노량진동 267-6",
        "매물특징": "-",
        "공급/전용면적": "",
        "해당층/총층": "중/16층",
        "방수/욕실수": "1/1개",
        "관리비": "8만원 상세보기",
        "입주 가능일": "2025년 3월 29일 협의가능",
        "방향": "남향(거실 기준)",
        "URL": "https://new.land.naver.com/houses?articleNo=2513864154",
        "메인사진": "https://landthumb-phinf.pstatic.net/20250315_16/1742017630890xPYzP_JPEG/1742017172767180.jpg?type=m400_350"
    },
    {
        "매물번호": "2513903439",
        "매물유형": "오피스텔",
        "거래유형": "월세",
        "가격": "1,000/80",
        "소재지": "서울시 동작구 노량진동 267-6",
        "매물특징": "0. 노량진역 역세권 신축급 원룸 오피스텔 귀한 월세 전입신고 가능",
        "공급/전용면적": "",
        "해당층/총층": "중/16층",
        "방수/욕실수": "1/1개",
        "관리비": "10만원 상세보기",
        "입주 가능일": "2025년 03월 하순 협의가능",
        "방향": "남서향(거실 기준)",
        "URL": "https://new.land.naver.com/houses?articleNo=2513903439",
        "메인사진": "https://landthumb-phinf.pstatic.net/20250315_110/1742029688038vEgCF_JPEG/KakaoTalk_20240613_155644709.jpg?type=m400_350"
    },
    {
        "매물번호": "2513180463",
        "매물유형": "오피스텔",
        "거래유형": "월세",
        "가격": "1억 9,000/5",
        "소재지": "서울시 동작구 노량진동 266-4",
        "매물특징": "0. 노량진역9호선,1호선 역세권 오피 원룸 대출,보험,전입가능",
        "공급/전용면적": "",
        "해당층/총층": "고/18층",
        "방수/욕실수": "1/1개",
        "관리비": "10만원 상세보기",
        "입주 가능일": "2025년 06월 중순 협의가능",
        "방향": "북동향(거실 기준)",
        "URL": "https://new.land.naver.com/houses?articleNo=2513180463",
        "메인사진": "https://landthumb-phinf.pstatic.net/20250312_129/1741768072380RlPew_JPEG/KakaoTalk_20210805_133428399.jpg?type=m400_350"
    },
    {
        "매물번호": "2511396565",
        "매물유형": "오피스텔",
        "거래유형": "월세",
        "가격": "1억 8,500/7",
        "소재지": "서울시 동작구 노량진동 266-4",
        "매물특징": "신축4년차 노량진역 도보5분 한강조망최고 임대사업자",
        "공급/전용면적": "",
        "해당층/총층": "15/18층",
        "방수/욕실수": "1/1개",
        "관리비": "9만원 상세보기",
        "입주 가능일": "2025년 6월 28일",
        "방향": "북서향(거실 기준)",
        "URL": "https://new.land.naver.com/houses?articleNo=2511396565",
        "메인사진": null
    },
    {
        "매물번호": "2511255139",
        "매물유형": "오피스텔",
        "거래유형": "전세",
        "가격": "2억 4,000",
        "소재지": "서울시 동작구 노량진동 266-4",
        "매물특징": "노량진대로변 신축급 1.5룸 풀옵션 남향 오피스텔 대출 보증보험",
        "공급/전용면적": "",
        "해당층/총층": "17/18층",
        "방수/욕실수": "1/1개",
        "관리비": "10만원 상세보기",
        "입주 가능일": "2025년 05월 중순",
        "방향": "남향(안방 기준)",
        "URL": "https://new.land.naver.com/houses?articleNo=2511255139",
        "메인사진": "https://landthumb-phinf.pstatic.net/20250311_278/1741666700023vFnLy_JPEG/KakaoTalk_20230715_110940447_01.jpg?type=m400_350"
    },
    {
        "매물번호": "2514339185",
        "매물유형": "오피스텔",
        "거래유형": "월세",
        "가격": "1,000/79억",
        "소재지": "서울시 동작구 노량진동 267-6",
        "매물특징": "지하철 1,9 호선을 이용할수 있어 직장인들의 출퇴근이 아주 편리합니다",
        "공급/전용면적": "",
        "해당층/총층": "중/16층",
        "방수/욕실수": "1/1개",
        "관리비": "20만 2,500원 상세보기",
        "입주 가능일": "2025년 4월 1일 협의가능",
        "방향": "동향(거실 기준)",
        "URL": "https://new.land.naver.com/houses?articleNo=2514339185",
        "메인사진": null
    },
    {
        "매물번호": "2513235667",
        "매물유형": "오피스텔",
        "거래유형": "월세",
        "가격": "1,000/90",
        "소재지": "서울시 동작구 노량진동 16-1",
        "매물특징": "전입안하는조건입니다",
        "공급/전용면적": "",
        "해당층/총층": "중/18층",
        "방수/욕실수": "1/1개",
        "관리비": "13만원 상세보기",
        "입주 가능일": "즉시입주",
        "방향": "남향(거실 기준)",
        "URL": "https://new.land.naver.com/houses?articleNo=2513235667",
        "메인사진": "https://landthumb-phinf.pstatic.net/20250313_209/1741836767440vWDAS_JPEG/20210217_080610.jpg?type=m400_350"
    },
    {
        "매물번호": "2512910154",
        "매물유형": "오피스텔",
        "거래유형": "월세",
        "가격": "1,000/70",
        "소재지": "서울시 동작구 노량진동 194-3",
        "매물특징": "대로변에 위치해 안전한 오피스텔입니다.",
        "공급/전용면적": "",
        "해당층/총층": "13/15층",
        "방수/욕실수": "1/1개",
        "관리비": "12만원 상세보기",
        "입주 가능일": "2025년 4월 30일",
        "방향": "남향(안방 기준)",
        "URL": "https://new.land.naver.com/houses?articleNo=2512910154",
        "메인사진": "https://landthumb-phinf.pstatic.net/20250317_243/17421835710297UKiJ_JPEG/%B9%E9%B8%ED1308%C8%A3_%282%29.jpg?type=m400_350"
    },
    {
        "매물번호": "2512967319",
        "매물유형": "오피스텔",
        "거래유형": "월세",
        "가격": "1,000/95",
        "소재지": "서울시 동작구 노량진동 16-1",
        "매물특징": "전입가능합니다 7월초입주가능합니다.",
        "공급/전용면적": "",
        "해당층/총층": "중/18층",
        "방수/욕실수": "1/1개",
        "관리비": "13만원 상세보기",
        "입주 가능일": "2025년 7월 5일 협의가능",
        "방향": "남향(거실 기준)",
        "URL": "https://new.land.naver.com/houses?articleNo=2512967319",
        "메인사진": "https://landthumb-phinf.pstatic.net/20250312_276/1741741056602crTlP_JPEG/20210227_141228.jpg?type=m400_350"
    },
    {
        "매물번호": "2512613739",
        "매물유형": "오피스텔",
        "거래유형": "월세",
        "가격": "1억/47억",
        "소재지": "서울시 동작구 노량진동 16-1",
        "매물특징": "북향,전입,버팀목, 보증보험가능 5천에 67만 가능",
        "공급/전용면적": "",
        "해당층/총층": "10/18층",
        "방수/욕실수": "1/1개",
        "관리비": "13만원 상세보기",
        "입주 가능일": "2026년 06월 하순",
        "방향": "북향(안방 기준)",
        "URL": "https://new.land.naver.com/houses?articleNo=2512613739",
        "메인사진": "https://landthumb-phinf.pstatic.net/20250310_225/1741592535284fNd77_JPEG/KakaoTalk_20201112_173330566_08.jpg?type=m400_350"
    },
    {
        "매물번호": "2512046589",
        "매물유형": "오피스텔",
        "거래유형": "월세",
        "가격": "2억/15",
        "소재지": "서울시 동작구 노량진동 16-1",
        "매물특징": "역세권 풀옵션 원룸 자주식 주차 입주일협의",
        "공급/전용면적": "",
        "해당층/총층": "고/18층",
        "방수/욕실수": "1/1개",
        "관리비": "12만원 상세보기",
        "입주 가능일": "2025년 5월 20일 협의가능",
        "방향": "남향(거실 기준)",
        "URL": "https://new.land.naver.com/houses?articleNo=2512046589",
        "메인사진": "https://landthumb-phinf.pstatic.net/20250307_193/1741332308973D3XqV_JPEG/2025030715374757805_36069_rot.jpg?type=m400_350"
    },
    {
        "매물번호": "2512768361",
        "매물유형": "오피스텔",
        "거래유형": "월세",
        "가격": "1,000/95",
        "소재지": "서울시 동작구 노량진동 16-1",
        "매물특징": "전입가능합니다 7월입주가능합니다.",
        "공급/전용면적": "",
        "해당층/총층": "중/18층",
        "방수/욕실수": "1/1개",
        "관리비": "13만원 상세보기",
        "입주 가능일": "2025년 7월 10일 협의가능",
        "방향": "북향(거실 기준)",
        "URL": "https://new.land.naver.com/houses?articleNo=2512768361",
        "메인사진": "https://landthumb-phinf.pstatic.net/20250311_203/1741684439032lT26P_JPEG/20210217_080610.jpg?type=m400_350"
    },
    {
        "매물번호": "2511756222",
        "매물유형": "오피스텔",
        "거래유형": "전세",
        "가격": "2억 4,000",
        "소재지": "서울시 동작구 노량진동 266-4",
        "매물특징": "0. 노량진역 역세권 신축 복층 오피스텔 전세 보증보험가능hug X",
        "공급/전용면적": "",
        "해당층/총층": "고/18층",
        "방수/욕실수": "1/1개",
        "관리비": "10만원 상세보기",
        "입주 가능일": "2025년 6월 29일 협의가능",
        "방향": "북서향(거실 기준)",
        "URL": "https://new.land.naver.com/houses?articleNo=2511756222",
        "메인사진": "https://landthumb-phinf.pstatic.net/20250306_285/17412433495692ybrh_JPEG/KakaoTalk_20230522_134610469_04.jpg?type=m400_350"
    },
    {
        "매물번호": "2513834704",
        "매물유형": "오피스텔",
        "거래유형": "월세",
        "가격": "3,000/75",
        "소재지": "서울시 동작구 노량진동 16-1",
        "매물특징": "신축 오피스텔 귀한 월세 매물입니다",
        "공급/전용면적": "",
        "해당층/총층": "저/18층",
        "방수/욕실수": "1/1개",
        "관리비": "10만원 상세보기",
        "입주 가능일": "2025년 4월 10일 협의가능",
        "방향": "남향(안방 기준)",
        "URL": "https://new.land.naver.com/houses?articleNo=2513834704",
        "메인사진": null
    },
    {
        "매물번호": "2512664126",
        "매물유형": "오피스텔",
        "거래유형": "월세",
        "가격": "3,000/77",
        "소재지": "서울시 동작구 노량진동 16-1",
        "매물특징": "전입가능합니다 6월입주가능합니다.",
        "공급/전용면적": "",
        "해당층/총층": "저/18층",
        "방수/욕실수": "1/1개",
        "관리비": "13만원 상세보기",
        "입주 가능일": "2025년 6월 30일 협의가능",
        "방향": "동향(거실 기준)",
        "URL": "https://new.land.naver.com/houses?articleNo=2512664126",
        "메인사진": "https://landthumb-phinf.pstatic.net/20250311_86/17416594284581fBG2_JPEG/20210217_080610.jpg?type=m400_350"
    },
    {
        "매물번호": "2512661389",
        "매물유형": "오피스텔",
        "거래유형": "월세",
        "가격": "1,000/76",
        "소재지": "서울시 동작구 노량진동 16-1",
        "매물특징": "전입가능합니다 3월22입주가능합니다.",
        "공급/전용면적": "",
        "해당층/총층": "저/18층",
        "방수/욕실수": "1/1개",
        "관리비": "13만원 상세보기",
        "입주 가능일": "2025년 3월 22일 협의가능",
        "방향": "동향(거실 기준)",
        "URL": "https://new.land.naver.com/houses?articleNo=2512661389",
        "메인사진": "https://landthumb-phinf.pstatic.net/20250317_90/1742204280504D9oD6_JPEG/20210217_080610.jpg?type=m400_350"
    },
    {
        "매물번호": "2510349788",
        "매물유형": "오피스텔",
        "거래유형": "월세",
        "가격": "2억/4",
        "소재지": "서울시 동작구 노량진동 16-1",
        "매물특징": "청년 버팀목대출가능 보증보험 가능 역세권 저렴한 반전세",
        "공급/전용면적": "",
        "해당층/총층": "8/18층",
        "방수/욕실수": "1/1개",
        "관리비": "12만원 상세보기",
        "입주 가능일": "2025년 5월 9일",
        "방향": "북향(안방 기준)",
        "URL": "https://new.land.naver.com/houses?articleNo=2510349788",
        "메인사진": "https://landthumb-phinf.pstatic.net/20250226_33/1740537127549zKUHc_JPEG/2025022610561468816_36069_ws.jpg?type=m400_350"
    },
    {
        "매물번호": "2513643578",
        "매물유형": "오피스텔",
        "거래유형": "월세",
        "가격": "1,000/90",
        "소재지": "서울시 동작구 노량진동 16-1",
        "매물특징": "즉시 입주,고층, 신축,풀옵션",
        "공급/전용면적": "",
        "해당층/총층": "중/18층",
        "방수/욕실수": "1/1개",
        "관리비": "12만원 상세보기",
        "입주 가능일": "즉시입주",
        "방향": "남향(안방 기준)",
        "URL": "https://new.land.naver.com/houses?articleNo=2513643578",
        "메인사진": null
    },
    {
        "매물번호": "2510060190",
        "매물유형": "오피스텔",
        "거래유형": "전세",
        "가격": "2억 4,000",
        "소재지": "서울시 동작구 노량진동 266-4",
        "매물특징": "보안철저 대로변 전경 멋진 신축4년 오피스텔 1,9호선 교통최고",
        "공급/전용면적": "",
        "해당층/총층": "18/18층",
        "방수/욕실수": "1/1개",
        "관리비": "10만원 상세보기",
        "입주 가능일": "즉시입주 협의가능",
        "방향": "북향(거실 기준)",
        "URL": "https://new.land.naver.com/houses?articleNo=2510060190",
        "메인사진": "https://landthumb-phinf.pstatic.net/20250224_217/1740391454436GIqVH_JPEG/20211007_114951.jpg?type=m400_350"
    },
    {
        "매물번호": "2509861731",
        "매물유형": "오피스텔",
        "거래유형": "월세",
        "가격": "1,000/70",
        "소재지": "서울시 동작구 노량진동 194-3",
        "매물특징": "실사 첨부. 실제 영상 첨부.가격좋고 위치 좋은 오피스텔",
        "공급/전용면적": "",
        "해당층/총층": "12/15층",
        "방수/욕실수": "1/1개",
        "관리비": "15만원 상세보기",
        "입주 가능일": "즉시입주 협의가능",
        "방향": "남향(거실 기준)",
        "URL": "https://new.land.naver.com/houses?articleNo=2509861731",
        "메인사진": "https://landthumb-phinf.pstatic.net/20250226_89/17405382653390AYGC_JPEG/KakaoTalk_20250224_184803780.jpg?type=m400_350"
    },
    {
        "매물번호": "2512661999",
        "매물유형": "오피스텔",
        "거래유형": "월세",
        "가격": "1,000/75억 5,000",
        "소재지": "서울시 동작구 노량진동 16-1",
        "매물특징": "남향, 밝은집 ,",
        "공급/전용면적": "",
        "해당층/총층": "저/18층",
        "방수/욕실수": "1/1개",
        "관리비": "12만원 상세보기",
        "입주 가능일": "2025년 5월 30일",
        "방향": "남향(거실 기준)",
        "URL": "https://new.land.naver.com/houses?articleNo=2512661999",
        "메인사진": null
    },
    {
        "매물번호": "2510417487",
        "매물유형": "오피스텔",
        "거래유형": "전세",
        "가격": "2억 1,000",
        "소재지": "서울시 동작구 노량진동 16-1",
        "매물특징": "대출가능,신축,풀옵션,즉시 입주가능협의",
        "공급/전용면적": "",
        "해당층/총층": "4/18층",
        "방수/욕실수": "1/1개",
        "관리비": "13만원 상세보기",
        "입주 가능일": "즉시입주 협의가능",
        "방향": "남향(거실 기준)",
        "URL": "https://new.land.naver.com/houses?articleNo=2510417487",
        "메인사진": null
    },
    {
        "매물번호": "2511220032",
        "매물유형": "오피스텔",
        "거래유형": "전세",
        "가격": "2억 1,000",
        "소재지": "서울시 동작구 노량진동 16-1",
        "매물특징": "주택임대사업자입니다 전입확정일자가능 전세대출가능",
        "공급/전용면적": "",
        "해당층/총층": "중/18층",
        "방수/욕실수": "1/1개",
        "관리비": "13만원 상세보기",
        "입주 가능일": "2025년 6월 25일",
        "방향": "북향(거실 기준)",
        "URL": "https://new.land.naver.com/houses?articleNo=2511220032",
        "메인사진": "https://landthumb-phinf.pstatic.net/20250304_152/1741065363573Q09qK_JPEG/20210305_144044.jpg?type=m400_350"
    },
    {
        "매물번호": "2511238124",
        "매물유형": "오피스텔",
        "거래유형": "전세",
        "가격": "2억 2,000",
        "소재지": "서울시 동작구 노량진동 16-1",
        "매물특징": "전입가능합니다 4월입주가능합니다.",
        "공급/전용면적": "",
        "해당층/총층": "저/18층",
        "방수/욕실수": "1/1개",
        "관리비": "13만원 상세보기",
        "입주 가능일": "2025년 4월 20일 협의가능",
        "방향": "동향(거실 기준)",
        "URL": "https://new.land.naver.com/houses?articleNo=2511238124",
        "메인사진": "https://landthumb-phinf.pstatic.net/20250304_74/1741074463015e09jC_JPEG/20210305_144044.jpg?type=m400_350"
    },
    {
        "매물번호": "2511939213",
        "매물유형": "오피스텔",
        "거래유형": "월세",
        "가격": "1,000/75",
        "소재지": "서울시 동작구 노량진동 57-1",
        "매물특징": "즉시입주가능한 노량진역세권 오피스텔",
        "공급/전용면적": "",
        "해당층/총층": "중/20층",
        "방수/욕실수": "1/1개",
        "관리비": "9만 8,800원 상세보기",
        "입주 가능일": "즉시입주",
        "방향": "서향(안방 기준)",
        "URL": "https://new.land.naver.com/houses?articleNo=2511939213",
        "메인사진": null
    },
    {
        "매물번호": "2509427930",
        "매물유형": "오피스텔",
        "거래유형": "월세",
        "가격": "1,000/90",
        "소재지": "서울시 동작구 노량진동 16-1",
        "매물특징": "일반사업자 부가세별도입니다 . 전입불가",
        "공급/전용면적": "",
        "해당층/총층": "저/18층",
        "방수/욕실수": "1/1개",
        "관리비": "13만원 상세보기",
        "입주 가능일": "2025년 2월 28일 협의가능",
        "방향": "서향(거실 기준)",
        "URL": "https://new.land.naver.com/houses?articleNo=2509427930",
        "메인사진": "https://landthumb-phinf.pstatic.net/20250221_167/1740107438619bnQyP_JPEG/prh_20210217_080610.jpg?type=m400_350"
    },
    {
        "매물번호": "2508672951",
        "매물유형": "오피스텔",
        "거래유형": "월세",
        "가격": "1,000/100",
        "소재지": "서울시 동작구 노량진동 16-1",
        "매물특징": "넓은호실,양창,남향,신축 풀옵션",
        "공급/전용면적": "",
        "해당층/총층": "14/18층",
        "방수/욕실수": "1/1개",
        "관리비": "12만원 상세보기",
        "입주 가능일": "2025년 4월 16일",
        "방향": "남서향(거실 기준)",
        "URL": "https://new.land.naver.com/houses?articleNo=2508672951",
        "메인사진": "https://landthumb-phinf.pstatic.net/20250305_214/1741166046492O64fd_JPEG/src_image_1.jpg?type=m400_350"
    },
    {
        "매물번호": "2508672951",
        "매물유형": "오피스텔",
        "거래유형": "월세",
        "가격": "1,000/100",
        "소재지": "서울시 동작구 노량진동 16-1",
        "매물특징": "넓은호실,양창,남향,신축 풀옵션",
        "공급/전용면적": "",
        "해당층/총층": "14/18층",
        "방수/욕실수": "1/1개",
        "관리비": "12만원 상세보기",
        "입주 가능일": "2025년 4월 16일",
        "방향": "남서향(거실 기준)",
        "URL": "https://new.land.naver.com/houses?articleNo=2508672951",
        "메인사진": "https://landthumb-phinf.pstatic.net/20250305_214/1741166046492O64fd_JPEG/src_image_1.jpg?type=m400_350"
    },
    {
        "매물번호": "2509348230",
        "매물유형": "오피스텔",
        "거래유형": "단기임대",
        "가격": "500/160",
        "소재지": "서울시 동작구 노량진동 16-1",
        "매물특징": "자주식주차가능, 노량진역 바로앞, 깔끔",
        "공급/전용면적": "",
        "해당층/총층": "저/18층",
        "방수/욕실수": "1/1개",
        "관리비": "10만원 상세보기",
        "입주 가능일": "2025년 2월 1일",
        "방향": "남향(거실 기준)",
        "URL": "https://new.land.naver.com/houses?articleNo=2509348230",
        "메인사진": "https://landthumb-phinf.pstatic.net/20250221_205/1740098176298Pe0Yg_JPEG/1740051985101537.jpg?type=m400_350"
    },
    {
        "매물번호": "2509347853",
        "매물유형": "오피스텔",
        "거래유형": "단기임대",
        "가격": "500/160",
        "소재지": "서울시 동작구 노량진동 16-1",
        "매물특징": "실입주가,한강뷰, 자주식주차가능, 노량진역 바로앞, 최고최고",
        "공급/전용면적": "",
        "해당층/총층": "중/18층",
        "방수/욕실수": "1/1개",
        "관리비": "10만원 상세보기",
        "입주 가능일": "2025년 2월 1일",
        "방향": "동향(거실 기준)",
        "URL": "https://new.land.naver.com/houses?articleNo=2509347853",
        "메인사진": "https://landthumb-phinf.pstatic.net/20250221_141/1740130105349i3o3B_JPEG/1740051144991403.jpg?type=m400_350"
    },
    {
        "매물번호": "2512591093",
        "매물유형": "오피스텔",
        "거래유형": "월세",
        "가격": "4,000/35",
        "소재지": "서울시 동작구 상도동 183-28",
        "매물특징": "장승배기역 초역세권 준신축급 관리잘된 풀옵션 오피스텔",
        "공급/전용면적": "",
        "해당층/총층": "4/10층",
        "방수/욕실수": "1/1개",
        "관리비": "13만원 상세보기",
        "입주 가능일": "2025년 5월 5일",
        "방향": "서향(안방 기준)",
        "URL": "https://new.land.naver.com/houses?articleNo=2512591093",
        "메인사진": "https://landthumb-phinf.pstatic.net/20250310_189/1741595679282Gz3em_JPEG/2025031014174008426_37113_ws.jpg?type=m400_350"
    },
    {
        "매물번호": "2512620982",
        "매물유형": "오피스텔",
        "거래유형": "단기임대",
        "가격": "30/60",
        "소재지": "서울시 동작구 상도1동 519-1",
        "매물특징": "상도1동 풀옵션 오피스텔 즉시입주 가능",
        "공급/전용면적": "",
        "해당층/총층": "6/9층",
        "방수/욕실수": "1/1개",
        "관리비": "8만원 상세보기",
        "입주 가능일": "즉시입주",
        "방향": "남서향(거실 기준)",
        "URL": "https://new.land.naver.com/houses?articleNo=2512620982",
        "메인사진": "https://landthumb-phinf.pstatic.net/20250310_257/17416077057624hVfi_JPEG/KakaoTalk_20240826_172109886_01.jpg?type=m400_350"
    },
    {
        "매물번호": "2512752228",
        "매물유형": "오피스텔",
        "거래유형": "월세",
        "가격": "3,000/143",
        "소재지": "서울시 동작구 사당동 1007-25",
        "매물특징": "2,4,7호선 트리플역세권 고층 탁트인 신축 풀옵션 1.5룸",
        "공급/전용면적": "",
        "해당층/총층": "12/12층",
        "방수/욕실수": "1/1개",
        "관리비": "13만원 상세보기",
        "입주 가능일": "즉시입주",
        "방향": "서향(거실 기준)",
        "URL": "https://new.land.naver.com/houses?articleNo=2512752228",
        "메인사진": "https://landthumb-phinf.pstatic.net/20250312_264/1741777441957j2nGl_JPEG/45c5a3af15d3ec4f2816dce66e683c3f.JPG?type=m400_350"
    },
    {
        "매물번호": "2511961050",
        "매물유형": "오피스텔",
        "거래유형": "월세",
        "가격": "3,000/138",
        "소재지": "서울시 동작구 사당동 1007-25",
        "매물특징": "신축 오피스텔 1.5룸 원룸 원거실 4,7, 2호선 이수 사당역세권",
        "공급/전용면적": "",
        "해당층/총층": "11/12층",
        "방수/욕실수": "1/1개",
        "관리비": "13만원 상세보기",
        "입주 가능일": "즉시입주 협의가능",
        "방향": "남서향(거실 기준)",
        "URL": "https://new.land.naver.com/houses?articleNo=2511961050",
        "메인사진": "https://landthumb-phinf.pstatic.net/20250307_118/1741349881451829kT_JPEG/a6fad23778e503b858f97167d7de005a.JPG?type=m400_350"
    },
    {
        "매물번호": "2511954356",
        "매물유형": "오피스텔",
        "거래유형": "월세",
        "가격": "3,000/143",
        "소재지": "서울시 동작구 사당동 1007-25",
        "매물특징": "4,7호선 이수역세권 1.5룸 오피스텔 뷰좋은 탑층",
        "공급/전용면적": "",
        "해당층/총층": "12/12층",
        "방수/욕실수": "1/1개",
        "관리비": "13만원 상세보기",
        "입주 가능일": "즉시입주 협의가능",
        "방향": "서향(거실 기준)",
        "URL": "https://new.land.naver.com/houses?articleNo=2511954356",
        "메인사진": "https://landthumb-phinf.pstatic.net/20250307_219/1741348083269TouQh_JPEG/01aba2b62672d46867f6d02f8be5ea97.JPG?type=m400_350"
    },
    {
        "매물번호": "2509359136",
        "매물유형": "오피스텔",
        "거래유형": "월세",
        "가격": "3,000/140",
        "소재지": "서울시 동작구 사당동 1007-25",
        "매물특징": "2,4,7호선 트리플역세권 고층 남향 신축 풀옵션 1.5룸",
        "공급/전용면적": "",
        "해당층/총층": "12/12층",
        "방수/욕실수": "1/1개",
        "관리비": "13만원 상세보기",
        "입주 가능일": "즉시입주",
        "방향": "남향(안방 기준)",
        "URL": "https://new.land.naver.com/houses?articleNo=2509359136",
        "메인사진": "https://landthumb-phinf.pstatic.net/20250224_61/1740392881509khMYg_JPEG/031f7f7f037fd46eb648cc7b6fc3e8d9.JPG?type=m400_350"
    },
    {
        "매물번호": "2514271890",
        "매물유형": "오피스텔",
        "거래유형": "월세",
        "가격": "1억 1,000/53",
        "소재지": "서울시 동작구 사당동 1007-13",
        "매물특징": "신축급 원룸 풀옵션 오피스텔 이수역 사당역 역세권",
        "공급/전용면적": "",
        "해당층/총층": "6/12층",
        "방수/욕실수": "1/1개",
        "관리비": "12만원 상세보기",
        "입주 가능일": "2025년 4월 30일 협의가능",
        "방향": "서향(거실 기준)",
        "URL": "https://new.land.naver.com/houses?articleNo=2514271890",
        "메인사진": "https://landthumb-phinf.pstatic.net/20250318_19/174225708781186LEp_JPEG/1741596932611109.jpg?type=m400_350"
    },
    {
        "매물번호": "2514271655",
        "매물유형": "오피스텔",
        "거래유형": "월세",
        "가격": "1억 2,000/48",
        "소재지": "서울시 동작구 사당동 1007-13",
        "매물특징": "신축급 원룸 풀옵션 오피스텔 이수역 사당역 역세권",
        "공급/전용면적": "",
        "해당층/총층": "6/12층",
        "방수/욕실수": "1/1개",
        "관리비": "12만원 상세보기",
        "입주 가능일": "2025년 4월 30일 협의가능",
        "방향": "서향(거실 기준)",
        "URL": "https://new.land.naver.com/houses?articleNo=2514271655",
        "메인사진": "https://landthumb-phinf.pstatic.net/20250318_36/1742262306726aNcRS_JPEG/1741596932611109.jpg?type=m400_350"
    },
    {
        "매물번호": "2514271812",
        "매물유형": "오피스텔",
        "거래유형": "월세",
        "가격": "9,000/63",
        "소재지": "서울시 동작구 사당동 1007-13",
        "매물특징": "신축급 원룸 풀옵션 오피스텔 이수역 사당역 역세권 컨디션 최상",
        "공급/전용면적": "",
        "해당층/총층": "6/12층",
        "방수/욕실수": "1/1개",
        "관리비": "12만원 상세보기",
        "입주 가능일": "2025년 4월 30일 협의가능",
        "방향": "서향(거실 기준)",
        "URL": "https://new.land.naver.com/houses?articleNo=2514271812",
        "메인사진": "https://landthumb-phinf.pstatic.net/20250318_201/17422627714795t3Yk_JPEG/1741596934494546.jpg?type=m400_350"
    },
    {
        "매물번호": "2514271719",
        "매물유형": "오피스텔",
        "거래유형": "월세",
        "가격": "1억 3,000/43",
        "소재지": "서울시 동작구 사당동 1007-13",
        "매물특징": "신축급 원룸 풀옵션 오피스텔 이수역 사당역 역세권",
        "공급/전용면적": "",
        "해당층/총층": "6/12층",
        "방수/욕실수": "1/1개",
        "관리비": "12만원 상세보기",
        "입주 가능일": "2025년 4월 30일 협의가능",
        "방향": "서향(거실 기준)",
        "URL": "https://new.land.naver.com/houses?articleNo=2514271719",
        "메인사진": "https://landthumb-phinf.pstatic.net/20250318_215/1742261488522Vx81j_JPEG/1741596934494546.jpg?type=m400_350"
    },
    {
        "매물번호": "2514165254",
        "매물유형": "오피스텔",
        "거래유형": "월세",
        "가격": "1억 3,000/43",
        "소재지": "서울시 동작구 사당동 1007-13",
        "매물특징": "4,7호선 이수초역세권 오피스텔 내부구조 좋음",
        "공급/전용면적": "",
        "해당층/총층": "6/12층",
        "방수/욕실수": "1/1개",
        "관리비": "12만원 상세보기",
        "입주 가능일": "즉시입주 협의가능",
        "방향": "서향(거실 기준)",
        "URL": "https://new.land.naver.com/houses?articleNo=2514165254",
        "메인사진": "https://landthumb-phinf.pstatic.net/20250317_92/17421948326498TXoO_JPEG/%B2%D9%B9%CC%B1%E2%B2%D9%B9%CC%B1%E2org_6538cb702c4ea.jpg?type=m400_350"
    },
    {
        "매물번호": "2514145412",
        "매물유형": "오피스텔",
        "거래유형": "월세",
        "가격": "3,000/30",
        "소재지": "서울시 동작구 사당동 212-1",
        "매물특징": "가성비좋아요,남향으로 채광좋음,원룸 풀옵션,보증금조정가능",
        "공급/전용면적": "",
        "해당층/총층": "3/6층",
        "방수/욕실수": "1/1개",
        "관리비": "5만원 상세보기",
        "입주 가능일": "즉시입주 협의가능",
        "방향": "남향(안방 기준)",
        "URL": "https://new.land.naver.com/houses?articleNo=2514145412",
        "메인사진": null
    },
    {
        "매물번호": "2513933337",
        "매물유형": "오피스텔",
        "거래유형": "월세",
        "가격": "1억/58",
        "소재지": "서울시 동작구 사당동 1007-13",
        "매물특징": "신축급 원룸 풀옵션 오피스텔 이수역 사당역 역세권",
        "공급/전용면적": "",
        "해당층/총층": "6/12층",
        "방수/욕실수": "1/1개",
        "관리비": "12만원 상세보기",
        "입주 가능일": "2025년 3월 31일 협의가능",
        "방향": "서향(거실 기준)",
        "URL": "https://new.land.naver.com/houses?articleNo=2513933337",
        "메인사진": "https://landthumb-phinf.pstatic.net/20250317_216/1742172104540L4OVL_JPEG/1741596932611109.jpg?type=m400_350"
    },
    {
        "매물번호": "2513268693",
        "매물유형": "오피스텔",
        "거래유형": "월세",
        "가격": "1억/58",
        "소재지": "서울시 동작구 사당동 1007-13",
        "매물특징": "이수역 가까운 1룸 오피스텔, 안전, 신축급. 깔끔, 주차가능",
        "공급/전용면적": "",
        "해당층/총층": "6/12층",
        "방수/욕실수": "1/1개",
        "관리비": "12만원 상세보기",
        "입주 가능일": "2025년 05월 초순 협의가능",
        "방향": "남동향(거실 기준)",
        "URL": "https://new.land.naver.com/houses?articleNo=2513268693",
        "메인사진": "https://landthumb-phinf.pstatic.net/20250313_179/1741836835778isjba_JPEG/1741571625811677.jpg?type=m400_350"
    },
    {
        "매물번호": "2513403013",
        "매물유형": "오피스텔",
        "거래유형": "월세",
        "가격": "7,000/73",
        "소재지": "서울시 동작구 사당동 1007-13",
        "매물특징": "신축급 원룸 풀옵션 오피스텔 이수역 사당역 역세권",
        "공급/전용면적": "",
        "해당층/총층": "6/12층",
        "방수/욕실수": "1/1개",
        "관리비": "12만원 상세보기",
        "입주 가능일": "2025년 4월 30일 협의가능",
        "방향": "서향(거실 기준)",
        "URL": "https://new.land.naver.com/houses?articleNo=2513403013",
        "메인사진": "https://landthumb-phinf.pstatic.net/20250317_186/1742168407278RKuMH_JPEG/1741596932611109.jpg?type=m400_350"
    },
    {
        "매물번호": "2513385856",
        "매물유형": "오피스텔",
        "거래유형": "월세",
        "가격": "1억 3,000/43",
        "소재지": "서울시 동작구 사당동 1007-13",
        "매물특징": "이수역 역세권 깔끔한 풀옵션 오피스텔",
        "공급/전용면적": "",
        "해당층/총층": "6/12층",
        "방수/욕실수": "1/1개",
        "관리비": "12만원 상세보기",
        "입주 가능일": "즉시입주",
        "방향": "서향(안방 기준)",
        "URL": "https://new.land.naver.com/houses?articleNo=2513385856",
        "메인사진": "https://landthumb-phinf.pstatic.net/20250313_153/1741843778201ony1V_JPEG/1741841505136335.jpg?type=m400_350"
    },
    {
        "매물번호": "2514391808",
        "매물유형": "오피스텔",
        "거래유형": "월세",
        "가격": "1억 5,000/65",
        "소재지": "서울시 동작구 사당동 1007-13",
        "매물특징": "초역세권 신축 오피스텔 1.5룸 고층 보증금 조절가능 안전한 집",
        "공급/전용면적": "",
        "해당층/총층": "5/12층",
        "방수/욕실수": "1/1개",
        "관리비": "14만원 상세보기",
        "입주 가능일": "즉시입주",
        "방향": "남향(거실 기준)",
        "URL": "https://new.land.naver.com/houses?articleNo=2514391808",
        "메인사진": "https://landthumb-phinf.pstatic.net/20250318_191/17422775818939TXnS_JPEG/gold4440_1647112003_1.jpg?type=m400_350"
    },
    {
        "매물번호": "2513256735",
        "매물유형": "오피스텔",
        "거래유형": "월세",
        "가격": "1억 3,000/43",
        "소재지": "서울시 동작구 사당동 1007-13",
        "매물특징": "이수역세권 도보 3분 신축급 원룸 보증금 조절가능",
        "공급/전용면적": "",
        "해당층/총층": "중/12층",
        "방수/욕실수": "1/1개",
        "관리비": "12만원 상세보기",
        "입주 가능일": "2025년 5월 1일 협의가능",
        "방향": "남동향(안방 기준)",
        "URL": "https://new.land.naver.com/houses?articleNo=2513256735",
        "메인사진": "https://landthumb-phinf.pstatic.net/20250313_84/1741834896722AmRPX_JPEG/IMG_4177.JPG?type=m400_350"
    },
    {
        "매물번호": "2513819298",
        "매물유형": "오피스텔",
        "거래유형": "월세",
        "가격": "5,000/90",
        "소재지": "서울시 동작구 사당동 1007-25",
        "매물특징": "-",
        "공급/전용면적": "",
        "해당층/총층": "11/12층",
        "방수/욕실수": "1/1개",
        "관리비": "13만원 상세보기",
        "입주 가능일": "2025년 3월 30일 협의가능",
        "방향": "북향(안방 기준)",
        "URL": "https://new.land.naver.com/houses?articleNo=2513819298",
        "메인사진": "https://landthumb-phinf.pstatic.net/20250315_18/1742011797401FFUpj_JPEG/8481741946359Vd.jpg?type=m400_350"
    },
    {
        "매물번호": "2513734331",
        "매물유형": "오피스텔",
        "거래유형": "월세",
        "가격": "3,000/135",
        "소재지": "서울시 동작구 사당동 1007-25",
        "매물특징": "이수역 초역세권 신축 풀옵션 넓고 전망 좋은 1.5룸",
        "공급/전용면적": "",
        "해당층/총층": "8/12층",
        "방수/욕실수": "1/1개",
        "관리비": "13만원 상세보기",
        "입주 가능일": "2025년 4월 20일 협의가능",
        "방향": "서향(안방 기준)",
        "URL": "https://new.land.naver.com/houses?articleNo=2513734331",
        "메인사진": "https://landthumb-phinf.pstatic.net/20250315_244/1741999519532JdKbY_JPEG/S_38531741943552DD.jpg?type=m400_350"
    },
    {
        "매물번호": "2513468225",
        "매물유형": "오피스텔",
        "거래유형": "월세",
        "가격": "3,000/135",
        "소재지": "서울시 동작구 사당동 1007-25",
        "매물특징": "4호선 7호선 역세권 5분거리 오피스텔. 언제라도 보실 수 있음.",
        "공급/전용면적": "",
        "해당층/총층": "8/12층",
        "방수/욕실수": "1/1개",
        "관리비": "13만원 상세보기",
        "입주 가능일": "즉시입주",
        "방향": "서향(거실 기준)",
        "URL": "https://new.land.naver.com/houses?articleNo=2513468225",
        "메인사진": null
    },
    {
        "매물번호": "2513398427",
        "매물유형": "오피스텔",
        "거래유형": "월세",
        "가격": "2,000/105",
        "소재지": "서울시 동작구 사당동 1007-25",
        "매물특징": "신축 오피트텔, 이수역 초역세권 보증금 조정 가능.",
        "공급/전용면적": "",
        "해당층/총층": "11/12층",
        "방수/욕실수": "1/1개",
        "관리비": "12만원 상세보기",
        "입주 가능일": "즉시입주 협의가능",
        "방향": "북서향(안방 기준)",
        "URL": "https://new.land.naver.com/houses?articleNo=2513398427",
        "메인사진": "https://landthumb-phinf.pstatic.net/20250313_23/1741846347164ukzai_JPEG/KakaoTalk_20250313_142010114_02_%281%29.jpg?type=m400_350"
    },
    {
        "매물번호": "2513315167",
        "매물유형": "오피스텔",
        "거래유형": "월세",
        "가격": "3,000/143",
        "소재지": "서울시 동작구 사당동 1007-25",
        "매물특징": "2,4,7호선 트리플역세권 고층 탁트인 신축 풀옵션 1.5룸",
        "공급/전용면적": "",
        "해당층/총층": "12/12층",
        "방수/욕실수": "1/1개",
        "관리비": "13만원 상세보기",
        "입주 가능일": "즉시입주",
        "방향": "서향(거실 기준)",
        "URL": "https://new.land.naver.com/houses?articleNo=2513315167",
        "메인사진": "https://landthumb-phinf.pstatic.net/20250313_247/1741848770579Bqy3d_JPEG/20241227_150616.jpg?type=m400_350"
    },
    {
        "매물번호": "2513387279",
        "매물유형": "오피스텔",
        "거래유형": "월세",
        "가격": "2억 5,000/25",
        "소재지": "서울시 동작구 사당동 1007-25",
        "매물특징": "-",
        "공급/전용면적": "",
        "해당층/총층": "12/12층",
        "방수/욕실수": "1/1개",
        "관리비": "1만 3,000원 상세보기",
        "입주 가능일": "즉시입주 협의가능",
        "방향": "서향(안방 기준)",
        "URL": "https://new.land.naver.com/houses?articleNo=2513387279",
        "메인사진": "https://landthumb-phinf.pstatic.net/20250314_180/1741927137100TW92N_JPEG/KakaoTalk_20250207_155418818_01.jpg?type=m400_350"
    },
    {
        "매물번호": "2512923790",
        "매물유형": "오피스텔",
        "거래유형": "전세",
        "가격": "2억 2,000",
        "소재지": "서울시 동작구 사당동 1007-25",
        "매물특징": "허그보증보험, 마지막 한개, 럭셔리 오피",
        "공급/전용면적": "",
        "해당층/총층": "11/12층",
        "방수/욕실수": "1/1개",
        "관리비": "12만원 상세보기",
        "입주 가능일": "즉시입주 협의가능",
        "방향": "북서향(안방 기준)",
        "URL": "https://new.land.naver.com/houses?articleNo=2512923790",
        "메인사진": "https://landthumb-phinf.pstatic.net/20250315_12/1742024663141eDVRc_JPEG/KakaoTalk_20241005_101421556_02.jpg?type=m400_350"
    },
    {
        "매물번호": "2512923790",
        "매물유형": "오피스텔",
        "거래유형": "전세",
        "가격": "2억 2,000",
        "소재지": "서울시 동작구 사당동 1007-25",
        "매물특징": "허그보증보험, 마지막 한개, 럭셔리 오피",
        "공급/전용면적": "",
        "해당층/총층": "11/12층",
        "방수/욕실수": "1/1개",
        "관리비": "12만원 상세보기",
        "입주 가능일": "즉시입주 협의가능",
        "방향": "북서향(안방 기준)",
        "URL": "https://new.land.naver.com/houses?articleNo=2512923790",
        "메인사진": "https://landthumb-phinf.pstatic.net/20250315_12/1742024663141eDVRc_JPEG/KakaoTalk_20241005_101421556_02.jpg?type=m400_350"
    },
    {
        "매물번호": "2512242744",
        "매물유형": "오피스텔",
        "거래유형": "월세",
        "가격": "2,000/60",
        "소재지": "서울시 동작구 사당동 142-1",
        "매물특징": "귀한 오피스텔",
        "공급/전용면적": "",
        "해당층/총층": "6/9층",
        "방수/욕실수": "1/1개",
        "관리비": "11만 4,500원 상세보기",
        "입주 가능일": "2025년 4월 7일",
        "방향": "남서향(안방 기준)",
        "URL": "https://new.land.naver.com/houses?articleNo=2512242744",
        "메인사진": null
    },
    {
        "매물번호": "2513487526",
        "매물유형": "오피스텔",
        "거래유형": "월세",
        "가격": "3,000/135",
        "소재지": "서울시 동작구 사당동 1007-25",
        "매물특징": "신축 오피스텔 뷰좋음 보증금조절가능",
        "공급/전용면적": "",
        "해당층/총층": "중/12층",
        "방수/욕실수": "1/1개",
        "관리비": "13만원 상세보기",
        "입주 가능일": "즉시입주 협의가능",
        "방향": "서향(거실 기준)",
        "URL": "https://new.land.naver.com/houses?articleNo=2513487526",
        "메인사진": null
    },
    {
        "매물번호": "2511623193",
        "매물유형": "오피스텔",
        "거래유형": "월세",
        "가격": "3,000/140",
        "소재지": "서울시 동작구 사당동 1007-25",
        "매물특징": "2,4,7호선 트리플역세권 고층 남향 신축 풀옵션 1.5룸",
        "공급/전용면적": "",
        "해당층/총층": "12/12층",
        "방수/욕실수": "1/1개",
        "관리비": "13만원 상세보기",
        "입주 가능일": "즉시입주",
        "방향": "남향(안방 기준)",
        "URL": "https://new.land.naver.com/houses?articleNo=2511623193",
        "메인사진": "https://landthumb-phinf.pstatic.net/20250306_54/1741228908785DF7Qh_JPEG/20241227_154707.jpg?type=m400_350"
    },
    {
        "매물번호": "2511992373",
        "매물유형": "오피스텔",
        "거래유형": "월세",
        "가격": "1억 2,000/34",
        "소재지": "서울시 동작구 사당동 1007-13",
        "매물특징": "이수역 초역세권 신축급 오피스텔 삼중보안 안전한집",
        "공급/전용면적": "",
        "해당층/총층": "3/12층",
        "방수/욕실수": "1/1개",
        "관리비": "11만원 상세보기",
        "입주 가능일": "즉시입주",
        "방향": "남향(거실 기준)",
        "URL": "https://new.land.naver.com/houses?articleNo=2511992373",
        "메인사진": "https://landthumb-phinf.pstatic.net/20250307_263/1741330459544e5jcX_JPEG/gold4440_1646840445_1.jpg?type=m400_350"
    },
    {
        "매물번호": "2511959019",
        "매물유형": "오피스텔",
        "거래유형": "월세",
        "가격": "3,000/138",
        "소재지": "서울시 동작구 사당동 1007-25",
        "매물특징": "2,4,7호선 이수 사당역세권 신축 1.5룸 풀옵션 오피스텔 남향",
        "공급/전용면적": "",
        "해당층/총층": "11/12층",
        "방수/욕실수": "1/1개",
        "관리비": "13만원 상세보기",
        "입주 가능일": "즉시입주 협의가능",
        "방향": "남서향(거실 기준)",
        "URL": "https://new.land.naver.com/houses?articleNo=2511959019",
        "메인사진": "https://landthumb-phinf.pstatic.net/20250307_57/1741322204089g6IR5_JPEG/org_67ca60c02a571.jpg?type=m400_350"
    },
    {
        "매물번호": "2511948861",
        "매물유형": "오피스텔",
        "거래유형": "월세",
        "가격": "3,000/143",
        "소재지": "서울시 동작구 사당동 1007-25",
        "매물특징": "4,7호선 이수역세권 1.5룸 원룸원거실 오피스텔 신축 첫입주",
        "공급/전용면적": "",
        "해당층/총층": "12/12층",
        "방수/욕실수": "1/1개",
        "관리비": "13만원 상세보기",
        "입주 가능일": "즉시입주 협의가능",
        "방향": "서향(거실 기준)",
        "URL": "https://new.land.naver.com/houses?articleNo=2511948861",
        "메인사진": "https://landthumb-phinf.pstatic.net/20250307_25/17413194568331ipVA_JPEG/org_67bd999bd4eba.jpg?type=m400_350"
    },
    {
        "매물번호": "2511802125",
        "매물유형": "오피스텔",
        "거래유형": "전세",
        "가격": "1억",
        "소재지": "서울시 동작구 사당동 1007-29",
        "매물특징": "신축형이며 풀옵션이고 교통짱입니다",
        "공급/전용면적": "",
        "해당층/총층": "5/6층",
        "방수/욕실수": "1/1개",
        "관리비": "10만원 상세보기",
        "입주 가능일": "즉시입주",
        "방향": "남향(거실 기준)",
        "URL": "https://new.land.naver.com/houses?articleNo=2511802125",
        "메인사진": null
    },
    {
        "매물번호": "2509983738",
        "매물유형": "오피스텔",
        "거래유형": "월세",
        "가격": "5,000/110",
        "소재지": "서울시 동작구 사당동 1049-8",
        "매물특징": "신축급 오피스텔 1.5룸 풀옵션 컨디션 최상 사당역 역세권",
        "공급/전용면적": "",
        "해당층/총층": "5/10층",
        "방수/욕실수": "1/1개",
        "관리비": "11만원 상세보기",
        "입주 가능일": "2025년 3월 22일 협의가능",
        "방향": "남서향(거실 기준)",
        "URL": "https://new.land.naver.com/houses?articleNo=2509983738",
        "메인사진": "https://landthumb-phinf.pstatic.net/20250224_13/1740383279205U3nSa_JPEG/1739780459834632.jpg?type=m400_350"
    },
    {
        "매물번호": "2509983738",
        "매물유형": "오피스텔",
        "거래유형": "월세",
        "가격": "5,000/110",
        "소재지": "서울시 동작구 사당동 1049-8",
        "매물특징": "신축급 오피스텔 1.5룸 풀옵션 컨디션 최상 사당역 역세권",
        "공급/전용면적": "",
        "해당층/총층": "5/10층",
        "방수/욕실수": "1/1개",
        "관리비": "11만원 상세보기",
        "입주 가능일": "2025년 3월 22일 협의가능",
        "방향": "남서향(거실 기준)",
        "URL": "https://new.land.naver.com/houses?articleNo=2509983738",
        "메인사진": "https://landthumb-phinf.pstatic.net/20250224_13/1740383279205U3nSa_JPEG/1739780459834632.jpg?type=m400_350"
    },
    {
        "매물번호": "2510819804",
        "매물유형": "오피스텔",
        "거래유형": "월세",
        "가격": "5,000/160",
        "소재지": "서울시 동작구 사당동 1007-25",
        "매물특징": "이수역 도보2분, 전월세 선택가능 신축 오피스텔",
        "공급/전용면적": "",
        "해당층/총층": "3/12층",
        "방수/욕실수": "2/1개",
        "관리비": "15만원 상세보기",
        "입주 가능일": "즉시입주 협의가능",
        "방향": "남동향(거실 기준)",
        "URL": "https://new.land.naver.com/houses?articleNo=2510819804",
        "메인사진": "https://landthumb-phinf.pstatic.net/20250304_75/1741071527885L6Kqd_JPEG/202502281911438537532228_4734103884_40570_rot.jpg?type=m400_350"
    },
    {
        "매물번호": "2508648545",
        "매물유형": "오피스텔",
        "거래유형": "월세",
        "가격": "3,000/120",
        "소재지": "서울시 동작구 사당동 1049-8",
        "매물특징": "신축급 오피스텔 1.5룸 풀옵션 컨디션 최상 사당역 역세권",
        "공급/전용면적": "",
        "해당층/총층": "5/10층",
        "방수/욕실수": "1/1개",
        "관리비": "11만원 상세보기",
        "입주 가능일": "2025년 3월 22일 협의가능",
        "방향": "남서향(거실 기준)",
        "URL": "https://new.land.naver.com/houses?articleNo=2508648545",
        "메인사진": "https://landthumb-phinf.pstatic.net/20250217_296/1739785059148w5VIs_JPEG/1739780185272242.jpg?type=m400_350"
    },
    {
        "매물번호": "2510198236",
        "매물유형": "오피스텔",
        "거래유형": "월세",
        "가격": "3,000/140",
        "소재지": "서울시 동작구 사당동 1007-25",
        "매물특징": "신축오피스텔 뷰좋은 탑층 1.5룸 4,7, 2호선 이수 사당역세권",
        "공급/전용면적": "",
        "해당층/총층": "12/12층",
        "방수/욕실수": "1/1개",
        "관리비": "13만원 상세보기",
        "입주 가능일": "즉시입주 협의가능",
        "방향": "남서향(거실 기준)",
        "URL": "https://new.land.naver.com/houses?articleNo=2510198236",
        "메인사진": "https://landthumb-phinf.pstatic.net/20250225_85/1740458731533LWj0Q_JPEG/org_67bc5ea03fd74.jpg?type=m400_350"
    },
    {
        "매물번호": "2508830589",
        "매물유형": "오피스텔",
        "거래유형": "전세",
        "가격": "3억 1,500",
        "소재지": "서울시 동작구 사당동 1007-25",
        "매물특징": "신축첫입주 풀옵션 1.5룸",
        "공급/전용면적": "",
        "해당층/총층": "12/12층",
        "방수/욕실수": "1/1개",
        "관리비": "13만원 상세보기",
        "입주 가능일": "즉시입주",
        "방향": "서향(거실 기준)",
        "URL": "https://new.land.naver.com/houses?articleNo=2508830589",
        "메인사진": "https://landthumb-phinf.pstatic.net/20250309_121/17415099033128if31_JPEG/S_56001739857939yC.jpg?type=m400_350"
    },
    {
        "매물번호": "2512385906",
        "매물유형": "오피스텔",
        "거래유형": "월세",
        "가격": "3,000/72",
        "소재지": "서울시 동작구 대방동 405-8",
        "매물특징": "-",
        "공급/전용면적": "",
        "해당층/총층": "5/9층",
        "방수/욕실수": "1/1개",
        "관리비": "23만 3,000원 상세보기",
        "입주 가능일": "즉시입주 협의가능",
        "방향": "남향(거실 기준)",
        "URL": "https://new.land.naver.com/houses?articleNo=2512385906",
        "메인사진": null
    },
    {
        "매물번호": "2513087430",
        "매물유형": "오피스텔",
        "거래유형": "월세",
        "가격": "3,000/64",
        "소재지": "서울시 동작구 대방동 405-8",
        "매물특징": "신대방삼거리역 초역세권 오피스텔",
        "공급/전용면적": "",
        "해당층/총층": "4/9층",
        "방수/욕실수": "1/1개",
        "관리비": "16만 5,000원 상세보기",
        "입주 가능일": "즉시입주 협의가능",
        "방향": "남동향(안방 기준)",
        "URL": "https://new.land.naver.com/houses?articleNo=2513087430",
        "메인사진": "https://landthumb-phinf.pstatic.net/20250312_193/1741753475696HV0C0_JPEG/1735199716076672.jpg?type=m400_350"
    },
    {
        "매물번호": "2512254334",
        "매물유형": "오피스텔",
        "거래유형": "월세",
        "가격": "1,000/65",
        "소재지": "서울시 동작구 대방동 394-26",
        "매물특징": "초 역세권 관리 잘되어서 깨긋하구 좋아요",
        "공급/전용면적": "",
        "해당층/총층": "중/11층",
        "방수/욕실수": "1/1개",
        "관리비": "7만원 상세보기",
        "입주 가능일": "2025년 7월 2일 협의가능",
        "방향": "북향(거실 기준)",
        "URL": "https://new.land.naver.com/houses?articleNo=2512254334",
        "메인사진": "https://landthumb-phinf.pstatic.net/20250308_165/1741415798329i9UFM_JPEG/1741412542544552.jpg?type=m400_350"
    },
    {
        "매물번호": "2510164202",
        "매물유형": "오피스텔",
        "거래유형": "월세",
        "가격": "1억/40",
        "소재지": "서울시 동작구 대방동 405-4",
        "매물특징": "대로변, 정말 큰평수 오피스텔, 안전한 매물",
        "공급/전용면적": "",
        "해당층/총층": "3/11층",
        "방수/욕실수": "1/1개",
        "관리비": "8만원 상세보기",
        "입주 가능일": "2025년 3월 15일 협의가능",
        "방향": "북동향(거실 기준)",
        "URL": "https://new.land.naver.com/houses?articleNo=2510164202",
        "메인사진": "https://landthumb-phinf.pstatic.net/20250225_37/17404544522412KwRQ_JPEG/%B2%D9%B9%CC%B1%E2%BD%C5%B4%EB%B9%E6%BB%EF%B0%C5%B8%AE%BF%AA%BF%C0%C7%C7%BD%BA%C5%DA_7.jpg?type=m400_350"
    },
    {
        "매물번호": "2510154731",
        "매물유형": "오피스텔",
        "거래유형": "월세",
        "가격": "7,000/55",
        "소재지": "서울시 동작구 대방동 405-4",
        "매물특징": "대로변, 큰평수 오피스텔, 바로 나갈방",
        "공급/전용면적": "",
        "해당층/총층": "3/11층",
        "방수/욕실수": "1/1개",
        "관리비": "8만원 상세보기",
        "입주 가능일": "2025년 3월 15일 협의가능",
        "방향": "북동향(거실 기준)",
        "URL": "https://new.land.naver.com/houses?articleNo=2510154731",
        "메인사진": "https://landthumb-phinf.pstatic.net/20250226_113/1740549011958Mj2ld_JPEG/%B2%D9%B9%CC%B1%E2IMG_1243.JPG?type=m400_350"
    },
    {
        "매물번호": "2510004392",
        "매물유형": "오피스텔",
        "거래유형": "월세",
        "가격": "3,000/72",
        "소재지": "서울시 동작구 대방동 405-8",
        "매물특징": "역도보10초 풀옵션 1.5룸 오피스텔 주차가능",
        "공급/전용면적": "",
        "해당층/총층": "5/9층",
        "방수/욕실수": "1/1개",
        "관리비": "23만 3,000원 상세보기",
        "입주 가능일": "2025년 6월 15일",
        "방향": "북동향(거실 기준)",
        "URL": "https://new.land.naver.com/houses?articleNo=2510004392",
        "메인사진": "https://landthumb-phinf.pstatic.net/20250224_57/1740385326798D7O38_JPEG/2025022414552832804_37113_ws.jpg?type=m400_350"
    },
    {
        "매물번호": "2509465423",
        "매물유형": "오피스텔",
        "거래유형": "월세",
        "가격": "3,000/72",
        "소재지": "서울시 동작구 대방동 405-8",
        "매물특징": "역 바로앞, 대로변, 귀한 1.5룸 오피스텔",
        "공급/전용면적": "",
        "해당층/총층": "5/9층",
        "방수/욕실수": "1/1개",
        "관리비": "24만원 상세보기",
        "입주 가능일": "2024년 6월 4일",
        "방향": "북동향(거실 기준)",
        "URL": "https://new.land.naver.com/houses?articleNo=2509465423",
        "메인사진": "https://landthumb-phinf.pstatic.net/20250221_253/1740113166087bMN20_JPEG/%B2%D9%B9%CC%B1%E2sh_KakaoTalk_20230515_132705425_02.jpg?type=m400_350"
    },
    {
        "매물번호": "2509465423",
        "매물유형": "오피스텔",
        "거래유형": "월세",
        "가격": "3,000/72",
        "소재지": "서울시 동작구 대방동 405-8",
        "매물특징": "역 바로앞, 대로변, 귀한 1.5룸 오피스텔",
        "공급/전용면적": "",
        "해당층/총층": "5/9층",
        "방수/욕실수": "1/1개",
        "관리비": "24만원 상세보기",
        "입주 가능일": "2024년 6월 4일",
        "방향": "북동향(거실 기준)",
        "URL": "https://new.land.naver.com/houses?articleNo=2509465423",
        "메인사진": "https://landthumb-phinf.pstatic.net/20250221_253/1740113166087bMN20_JPEG/%B2%D9%B9%CC%B1%E2sh_KakaoTalk_20230515_132705425_02.jpg?type=m400_350"
    },
    {
        "매물번호": "2508733588",
        "매물유형": "오피스텔",
        "거래유형": "월세",
        "가격": "3,000/63",
        "소재지": "서울시 동작구 대방동 405-8",
        "매물특징": "깔끔한 대로변 오피스텔 귀한 매물입니다",
        "공급/전용면적": "",
        "해당층/총층": "4/9층",
        "방수/욕실수": "1/1개",
        "관리비": "17만원 상세보기",
        "입주 가능일": "2025년 5월 19일 협의가능",
        "방향": "북동향(거실 기준)",
        "URL": "https://new.land.naver.com/houses?articleNo=2508733588",
        "메인사진": "https://landthumb-phinf.pstatic.net/20250310_147/1741587532919D7lmT_JPEG/15200713_20237515531415.JPG?type=m400_350"
    },
    {
        "매물번호": "2508733588",
        "매물유형": "오피스텔",
        "거래유형": "월세",
        "가격": "3,000/63",
        "소재지": "서울시 동작구 대방동 405-8",
        "매물특징": "깔끔한 대로변 오피스텔 귀한 매물입니다",
        "공급/전용면적": "",
        "해당층/총층": "4/9층",
        "방수/욕실수": "1/1개",
        "관리비": "17만원 상세보기",
        "입주 가능일": "2025년 5월 19일 협의가능",
        "방향": "북동향(거실 기준)",
        "URL": "https://new.land.naver.com/houses?articleNo=2508733588",
        "메인사진": "https://landthumb-phinf.pstatic.net/20250310_147/1741587532919D7lmT_JPEG/15200713_20237515531415.JPG?type=m400_350"
    },
    {
        "매물번호": "2514058309",
        "매물유형": "오피스텔",
        "거래유형": "전세",
        "가격": "2억 3,000",
        "소재지": "서울시 동작구 신대방동 342-15",
        "매물특징": "신대방삼거리역세권 허그버팀목가능",
        "공급/전용면적": "",
        "해당층/총층": "4/9층",
        "방수/욕실수": "1/1개",
        "관리비": "9만 5,000원 상세보기",
        "입주 가능일": "2025년 5월 1일 협의가능",
        "방향": "남동향(거실 기준)",
        "URL": "https://new.land.naver.com/houses?articleNo=2514058309",
        "메인사진": "https://landthumb-phinf.pstatic.net/20250317_269/1742181934587EqnCC_JPEG/673add56aae9e_origin.jpg?type=m400_350"
    },
    {
        "매물번호": "2513664115",
        "매물유형": "오피스텔",
        "거래유형": "전세",
        "가격": "2억 8,000",
        "소재지": "서울시 동작구 신대방동 342-15",
        "매물특징": "HUG청년버팀목 보증보험가입 대로변 신축급 투룸",
        "공급/전용면적": "",
        "해당층/총층": "4/9층",
        "방수/욕실수": "2/1개",
        "관리비": "5만 5,000원 상세보기",
        "입주 가능일": "즉시입주",
        "방향": "남향(거실 기준)",
        "URL": "https://new.land.naver.com/houses?articleNo=2513664115",
        "메인사진": "https://landthumb-phinf.pstatic.net/20250314_186/1741932908501GUatc_JPEG/2025031414313510417_37113_ws.jpg?type=m400_350"
    },
    {
        "매물번호": "2512525340",
        "매물유형": "오피스텔",
        "거래유형": "전세",
        "가격": "1억 6,000",
        "소재지": "서울시 동작구 신대방동 698",
        "매물특징": "신축급 오피스텔 귀한 전세, 2호선 구디역",
        "공급/전용면적": "",
        "해당층/총층": "4/9층",
        "방수/욕실수": "1/1개",
        "관리비": "16만원 상세보기",
        "입주 가능일": "2025년 03월 중순 협의가능",
        "방향": "동향(안방 기준)",
        "URL": "https://new.land.naver.com/houses?articleNo=2512525340",
        "메인사진": "https://landthumb-phinf.pstatic.net/20250310_60/1741589351752L31Rv_JPEG/2025031012080536573_37706_ws.jpg?type=m400_350"
    },
    {
        "매물번호": "2512525340",
        "매물유형": "오피스텔",
        "거래유형": "전세",
        "가격": "1억 6,000",
        "소재지": "서울시 동작구 신대방동 698",
        "매물특징": "신축급 오피스텔 귀한 전세, 2호선 구디역",
        "공급/전용면적": "",
        "해당층/총층": "4/9층",
        "방수/욕실수": "1/1개",
        "관리비": "16만원 상세보기",
        "입주 가능일": "2025년 03월 중순 협의가능",
        "방향": "동향(안방 기준)",
        "URL": "https://new.land.naver.com/houses?articleNo=2512525340",
        "메인사진": "https://landthumb-phinf.pstatic.net/20250310_60/1741589351752L31Rv_JPEG/2025031012080536573_37706_ws.jpg?type=m400_350"
    },
    {
        "매물번호": "2512525340",
        "매물유형": "오피스텔",
        "거래유형": "전세",
        "가격": "1억 6,000",
        "소재지": "서울시 동작구 신대방동 698",
        "매물특징": "신축급 오피스텔 귀한 전세, 2호선 구디역",
        "공급/전용면적": "",
        "해당층/총층": "4/9층",
        "방수/욕실수": "1/1개",
        "관리비": "16만원 상세보기",
        "입주 가능일": "2025년 03월 중순 협의가능",
        "방향": "동향(안방 기준)",
        "URL": "https://new.land.naver.com/houses?articleNo=2512525340",
        "메인사진": "https://landthumb-phinf.pstatic.net/20250310_60/1741589351752L31Rv_JPEG/2025031012080536573_37706_ws.jpg?type=m400_350"
    },
    {
        "매물번호": "2512525340",
        "매물유형": "오피스텔",
        "거래유형": "전세",
        "가격": "1억 6,000",
        "소재지": "서울시 동작구 신대방동 698",
        "매물특징": "신축급 오피스텔 귀한 전세, 2호선 구디역",
        "공급/전용면적": "",
        "해당층/총층": "4/9층",
        "방수/욕실수": "1/1개",
        "관리비": "16만원 상세보기",
        "입주 가능일": "2025년 03월 중순 협의가능",
        "방향": "동향(안방 기준)",
        "URL": "https://new.land.naver.com/houses?articleNo=2512525340",
        "메인사진": "https://landthumb-phinf.pstatic.net/20250310_60/1741589351752L31Rv_JPEG/2025031012080536573_37706_ws.jpg?type=m400_350"
    },
    {
        "매물번호": "2512525340",
        "매물유형": "오피스텔",
        "거래유형": "전세",
        "가격": "1억 6,000",
        "소재지": "서울시 동작구 신대방동 698",
        "매물특징": "신축급 오피스텔 귀한 전세, 2호선 구디역",
        "공급/전용면적": "",
        "해당층/총층": "4/9층",
        "방수/욕실수": "1/1개",
        "관리비": "16만원 상세보기",
        "입주 가능일": "2025년 03월 중순 협의가능",
        "방향": "동향(안방 기준)",
        "URL": "https://new.land.naver.com/houses?articleNo=2512525340",
        "메인사진": "https://landthumb-phinf.pstatic.net/20250310_60/1741589351752L31Rv_JPEG/2025031012080536573_37706_ws.jpg?type=m400_350"
    },
    {
        "매물번호": "2514252171",
        "매물유형": "오피스텔",
        "거래유형": "월세",
        "가격": "2억 3,000/10",
        "소재지": "서울시 동작구 신대방동 342-15",
        "매물특징": "허그버팀목 보증보험 가능하고 주차 엘베있는 풀옵션원룸원거실 오피스텔입니다",
        "공급/전용면적": "",
        "해당층/총층": "4/9층",
        "방수/욕실수": "1/1개",
        "관리비": "7만원 상세보기",
        "입주 가능일": "2025년 5월 1일 협의가능",
        "방향": "서향(거실 기준)",
        "URL": "https://new.land.naver.com/houses?articleNo=2514252171",
        "메인사진": "https://landthumb-phinf.pstatic.net/20250318_205/1742266860148jjyNC_JPEG/2025031718553145_19051_wt.jpg?type=m400_350"
    },
    {
        "매물번호": "2514094940",
        "매물유형": "오피스텔",
        "거래유형": "월세",
        "가격": "2억 3,000/9",
        "소재지": "서울시 동작구 신대방동 342-15",
        "매물특징": "HUG버팀목0 보증보험0 신축급 1.5룸 풀옵션 융자없음 주차반려가능",
        "공급/전용면적": "",
        "해당층/총층": "4/9층",
        "방수/욕실수": "1/1개",
        "관리비": "8만원 상세보기",
        "입주 가능일": "2025년 2월 4일 협의가능",
        "방향": "동향(거실 기준)",
        "URL": "https://new.land.naver.com/houses?articleNo=2514094940",
        "메인사진": "https://landthumb-phinf.pstatic.net/20250317_18/17421904111598MI5j_JPEG/2025031710565554844_37113_ws.jpg?type=m400_350"
    },
    {
        "매물번호": "2514094940",
        "매물유형": "오피스텔",
        "거래유형": "월세",
        "가격": "2억 3,000/9",
        "소재지": "서울시 동작구 신대방동 342-15",
        "매물특징": "HUG버팀목0 보증보험0 신축급 1.5룸 풀옵션 융자없음 주차반려가능",
        "공급/전용면적": "",
        "해당층/총층": "4/9층",
        "방수/욕실수": "1/1개",
        "관리비": "8만원 상세보기",
        "입주 가능일": "2025년 2월 4일 협의가능",
        "방향": "동향(거실 기준)",
        "URL": "https://new.land.naver.com/houses?articleNo=2514094940",
        "메인사진": "https://landthumb-phinf.pstatic.net/20250317_18/17421904111598MI5j_JPEG/2025031710565554844_37113_ws.jpg?type=m400_350"
    },
    {
        "매물번호": "2514094940",
        "매물유형": "오피스텔",
        "거래유형": "월세",
        "가격": "2억 3,000/9",
        "소재지": "서울시 동작구 신대방동 342-15",
        "매물특징": "HUG버팀목0 보증보험0 신축급 1.5룸 풀옵션 융자없음 주차반려가능",
        "공급/전용면적": "",
        "해당층/총층": "4/9층",
        "방수/욕실수": "1/1개",
        "관리비": "8만원 상세보기",
        "입주 가능일": "2025년 2월 4일 협의가능",
        "방향": "동향(거실 기준)",
        "URL": "https://new.land.naver.com/houses?articleNo=2514094940",
        "메인사진": "https://landthumb-phinf.pstatic.net/20250317_18/17421904111598MI5j_JPEG/2025031710565554844_37113_ws.jpg?type=m400_350"
    },
    {
        "매물번호": "2514094940",
        "매물유형": "오피스텔",
        "거래유형": "월세",
        "가격": "2억 3,000/9",
        "소재지": "서울시 동작구 신대방동 342-15",
        "매물특징": "HUG버팀목0 보증보험0 신축급 1.5룸 풀옵션 융자없음 주차반려가능",
        "공급/전용면적": "",
        "해당층/총층": "4/9층",
        "방수/욕실수": "1/1개",
        "관리비": "8만원 상세보기",
        "입주 가능일": "2025년 2월 4일 협의가능",
        "방향": "동향(거실 기준)",
        "URL": "https://new.land.naver.com/houses?articleNo=2514094940",
        "메인사진": "https://landthumb-phinf.pstatic.net/20250317_18/17421904111598MI5j_JPEG/2025031710565554844_37113_ws.jpg?type=m400_350"
    },
    {
        "매물번호": "2514094940",
        "매물유형": "오피스텔",
        "거래유형": "월세",
        "가격": "2억 3,000/9",
        "소재지": "서울시 동작구 신대방동 342-15",
        "매물특징": "HUG버팀목0 보증보험0 신축급 1.5룸 풀옵션 융자없음 주차반려가능",
        "공급/전용면적": "",
        "해당층/총층": "4/9층",
        "방수/욕실수": "1/1개",
        "관리비": "8만원 상세보기",
        "입주 가능일": "2025년 2월 4일 협의가능",
        "방향": "동향(거실 기준)",
        "URL": "https://new.land.naver.com/houses?articleNo=2514094940",
        "메인사진": "https://landthumb-phinf.pstatic.net/20250317_18/17421904111598MI5j_JPEG/2025031710565554844_37113_ws.jpg?type=m400_350"
    },
    {
        "매물번호": "2513031326",
        "매물유형": "오피스텔",
        "거래유형": "월세",
        "가격": "1,000/90",
        "소재지": "서울시 동작구 신대방동 719",
        "매물특징": "전용12. 분리형 1.5룸으로 사업자만 가능함 , 내부 수리예정임.",
        "공급/전용면적": "",
        "해당층/총층": "저/25층",
        "방수/욕실수": "1/1개",
        "관리비": "10만원 상세보기",
        "입주 가능일": "즉시입주 협의가능",
        "방향": "서향(거실 기준)",
        "URL": "https://new.land.naver.com/houses?articleNo=2513031326",
        "메인사진": "https://landthumb-phinf.pstatic.net/20250312_184/1741745647320TCgwH_JPEG/1678845287701020.jpg?type=m400_350"
    },
    {
        "매물번호": "2514184371",
        "매물유형": "오피스텔",
        "거래유형": "월세",
        "가격": "2억 3,000/10",
        "소재지": "서울시 동작구 신대방동 342-15",
        "매물특징": "허그가능 보증보험 대출가능 새집컨디션1.5룸 초역세권 주차가능 꿀매물",
        "공급/전용면적": "",
        "해당층/총층": "4/9층",
        "방수/욕실수": "1/1개",
        "관리비": "7만원 상세보기",
        "입주 가능일": "2025년 5월 1일 협의가능",
        "방향": "서향(거실 기준)",
        "URL": "https://new.land.naver.com/houses?articleNo=2514184371",
        "메인사진": "https://landthumb-phinf.pstatic.net/20250317_203/1742204015943i4aPw_JPEG/2025031714533173_19051_wt.jpg?type=m400_350"
    },
    {
        "매물번호": "2514097536",
        "매물유형": "오피스텔",
        "거래유형": "월세",
        "가격": "2억 3,000/9",
        "소재지": "서울시 동작구 신대방동 342-15",
        "매물특징": "초초역세권 HUG 신축급의 1룸 1거실 햇살 및 뷰가조은 매물",
        "공급/전용면적": "",
        "해당층/총층": "4/9층",
        "방수/욕실수": "1/1개",
        "관리비": "7만원 상세보기",
        "입주 가능일": "2025년 5월 1일 협의가능",
        "방향": "남서향(거실 기준)",
        "URL": "https://new.land.naver.com/houses?articleNo=2514097536",
        "메인사진": "https://landthumb-phinf.pstatic.net/20250318_146/1742270929842OBVwO_JPEG/ggomadol_1647336996_4.jpg?type=m400_350"
    },
    {
        "매물번호": "2512096767",
        "매물유형": "오피스텔",
        "거래유형": "전세",
        "가격": "2억 4,000",
        "소재지": "서울시 동작구 신대방동 719",
        "매물특징": "전용12. 내부 깨끗함 , 1.5룸 분리형 , 전세보증보험 가입가능",
        "공급/전용면적": "",
        "해당층/총층": "저/25층",
        "방수/욕실수": "1/1개",
        "관리비": "10만원 상세보기",
        "입주 가능일": "즉시입주 협의가능",
        "방향": "서향(거실 기준)",
        "URL": "https://new.land.naver.com/houses?articleNo=2512096767",
        "메인사진": "https://landthumb-phinf.pstatic.net/20250308_227/1741395760887lQLbv_JPEG/1678845287701020.jpg?type=m400_350"
    },
    {
        "매물번호": "2514258235",
        "매물유형": "오피스텔",
        "거래유형": "월세",
        "가격": "2억 3,000/10",
        "소재지": "서울시 동작구 신대방동 342-15",
        "매물특징": "안전한집 신삼 초역세권 허그 보증보험 가능한 1.5룸 오피스텔입니다.",
        "공급/전용면적": "",
        "해당층/총층": "중/9층",
        "방수/욕실수": "2/1개",
        "관리비": "7만원 상세보기",
        "입주 가능일": "즉시입주 협의가능",
        "방향": "남동향(거실 기준)",
        "URL": "https://new.land.naver.com/houses?articleNo=2514258235",
        "메인사진": "https://landthumb-phinf.pstatic.net/20250318_243/1742260010170yru6e_JPEG/batch_KakaoTalk_20250317_200926788_03.jpg?type=m400_350"
    },
    {
        "매물번호": "2510750383",
        "매물유형": "오피스텔",
        "거래유형": "월세",
        "가격": "1,000/70",
        "소재지": "서울시 동작구 신대방동 395-73",
        "매물특징": "즉시입주,업무용,신림선2분,넓고쾌적,공동환영,주차편리,병원.공원앞",
        "공급/전용면적": "",
        "해당층/총층": "11/26층",
        "방수/욕실수": "1/1개",
        "관리비": "20만원 상세보기",
        "입주 가능일": "즉시입주 협의가능",
        "방향": "북향(거실 기준)",
        "URL": "https://new.land.naver.com/houses?articleNo=2510750383",
        "메인사진": null
    },
    {
        "매물번호": "2513128563",
        "매물유형": "오피스텔",
        "거래유형": "전세",
        "가격": "2억 9,000",
        "소재지": "서울시 동작구 신대방동 342-15",
        "매물특징": "신대방삼거리역 3분거리 귀한 2룸전세",
        "공급/전용면적": "",
        "해당층/총층": "저/9층",
        "방수/욕실수": "2/1개",
        "관리비": "8만원 상세보기",
        "입주 가능일": "즉시입주 협의가능",
        "방향": "남향(거실 기준)",
        "URL": "https://new.land.naver.com/houses?articleNo=2513128563",
        "메인사진": null
    },
    {
        "매물번호": "2508618584",
        "매물유형": "오피스텔",
        "거래유형": "월세",
        "가격": "1,000/75",
        "소재지": "서울시 동작구 신대방동 395-73",
        "매물특징": "건강관리에최적보라매병원,공원편리한교통환경무엇이든살수있는상권먹거리",
        "공급/전용면적": "",
        "해당층/총층": "8/26층",
        "방수/욕실수": "1/1개",
        "관리비": "30만원 상세보기",
        "입주 가능일": "2025년 3월 23일 협의가능",
        "방향": "남향(거실 기준)",
        "URL": "https://new.land.naver.com/houses?articleNo=2508618584",
        "메인사진": null
    },
    {
        "매물번호": "2508615129",
        "매물유형": "오피스텔",
        "거래유형": "월세",
        "가격": "1,000/75",
        "소재지": "서울시 동작구 신대방동 395-73",
        "매물특징": "건강관리에최적보라매병원,공원편리한교통환경.무엇이든살수있는상권.먹거리",
        "공급/전용면적": "",
        "해당층/총층": "8/26층",
        "방수/욕실수": "1/1개",
        "관리비": "30만원 상세보기",
        "입주 가능일": "2025년 3월 23일 협의가능",
        "방향": "남향(거실 기준)",
        "URL": "https://new.land.naver.com/houses?articleNo=2508615129",
        "메인사진": null
    },
    {
        "매물번호": "2508613711",
        "매물유형": "오피스텔",
        "거래유형": "월세",
        "가격": "1,000/75",
        "소재지": "서울시 동작구 신대방동 395-73",
        "매물특징": "건강관리에최적보라매병원,공원편리한교통환경.무엇이든살수있는상권.먹거리",
        "공급/전용면적": "",
        "해당층/총층": "8/26층",
        "방수/욕실수": "1/1개",
        "관리비": "30만원 상세보기",
        "입주 가능일": "2025년 3월 23일 협의가능",
        "방향": "남향(거실 기준)",
        "URL": "https://new.land.naver.com/houses?articleNo=2508613711",
        "메인사진": null
    },
    {
        "매물번호": "2508729784",
        "매물유형": "오피스텔",
        "거래유형": "월세",
        "가격": "1,000/65",
        "소재지": "서울시 동작구 신대방동 698",
        "매물특징": "업무용, 전입불가, 입주협의",
        "공급/전용면적": "",
        "해당층/총층": "고/9층",
        "방수/욕실수": "1/1개",
        "관리비": "10만원 상세보기",
        "입주 가능일": "즉시입주 협의가능",
        "방향": "동향(거실 기준)",
        "URL": "https://new.land.naver.com/houses?articleNo=2508729784",
        "메인사진": "https://landthumb-phinf.pstatic.net/20250309_185/1741496282986s2GIy_JPEG/1739841742856137.jpg?type=m400_350"
    }
]